cachubclient/__init__.py
cachubclient/client.py
cachubclient/version.py
cachubclient-0.3.1.dist-info/licenses/AUTHORS.rst
cachubclient-0.3.1.dist-info/licenses/LICENSE
cachubclient-0.3.1.dist-info/METADATA
cachubclient-0.3.1.dist-info/WHEEL
cachubclient-0.3.1.dist-info/top_level.txt
cachubclient-0.3.1.dist-info/RECORD
